setup.py
sample/__init__.py
sample/hello_world.py
sample_738.egg-info/PKG-INFO
sample_738.egg-info/SOURCES.txt
sample_738.egg-info/dependency_links.txt
sample_738.egg-info/top_level.txt