Metadata-Version: 2.1
Name: sample-738
Version: 0.0.1
Summary: This is a sample package
Author: AST-LW
